{
  "type": "GROUP",
"name": "Global Information",
"path": "",
"pathFormatted": "group_missing-name-b06d1",
"stats": {
    "name": "Global Information",
    "numberOfRequests": {
        "total": 8,
        "ok": 7,
        "ko": 1
    },
    "minResponseTime": {
        "total": 396,
        "ok": 396,
        "ko": 823
    },
    "maxResponseTime": {
        "total": 7301,
        "ok": 7301,
        "ko": 823
    },
    "meanResponseTime": {
        "total": 1486,
        "ok": 1581,
        "ko": 823
    },
    "standardDeviation": {
        "total": 2202,
        "ok": 2339,
        "ko": 0
    },
    "percentiles1": {
        "total": 741,
        "ok": 730,
        "ko": 823
    },
    "percentiles2": {
        "total": 771,
        "ok": 752,
        "ko": 823
    },
    "percentiles3": {
        "total": 5034,
        "ok": 5337,
        "ko": 823
    },
    "percentiles4": {
        "total": 6848,
        "ok": 6908,
        "ko": 823
    },
    "group1": {
        "name": "t < 800 ms",
        "count": 6,
        "percentage": 75
    },
    "group2": {
        "name": "800 ms < t < 1200 ms",
        "count": 0,
        "percentage": 0
    },
    "group3": {
        "name": "t > 1200 ms",
        "count": 1,
        "percentage": 13
    },
    "group4": {
        "name": "failed",
        "count": 1,
        "percentage": 13
    },
    "meanNumberOfRequestsPerSecond": {
        "total": 0.06153846153846154,
        "ok": 0.05384615384615385,
        "ko": 0.007692307692307693
    }
},
"contents": {
"req_quote-price-for-4ae42": {
        "type": "REQUEST",
        "name": "QUOTE PRICE FOR OUTBOUND TRIP WITH ONE SLICE ONE SEGMENT ONE LEG.",
"path": "QUOTE PRICE FOR OUTBOUND TRIP WITH ONE SLICE ONE SEGMENT ONE LEG.",
"pathFormatted": "req_quote-price-for-4ae42",
"stats": {
    "name": "QUOTE PRICE FOR OUTBOUND TRIP WITH ONE SLICE ONE SEGMENT ONE LEG.",
    "numberOfRequests": {
        "total": 1,
        "ok": 1,
        "ko": 0
    },
    "minResponseTime": {
        "total": 656,
        "ok": 656,
        "ko": 0
    },
    "maxResponseTime": {
        "total": 656,
        "ok": 656,
        "ko": 0
    },
    "meanResponseTime": {
        "total": 656,
        "ok": 656,
        "ko": 0
    },
    "standardDeviation": {
        "total": 0,
        "ok": 0,
        "ko": 0
    },
    "percentiles1": {
        "total": 656,
        "ok": 656,
        "ko": 0
    },
    "percentiles2": {
        "total": 656,
        "ok": 656,
        "ko": 0
    },
    "percentiles3": {
        "total": 656,
        "ok": 656,
        "ko": 0
    },
    "percentiles4": {
        "total": 656,
        "ok": 656,
        "ko": 0
    },
    "group1": {
        "name": "t < 800 ms",
        "count": 1,
        "percentage": 100
    },
    "group2": {
        "name": "800 ms < t < 1200 ms",
        "count": 0,
        "percentage": 0
    },
    "group3": {
        "name": "t > 1200 ms",
        "count": 0,
        "percentage": 0
    },
    "group4": {
        "name": "failed",
        "count": 0,
        "percentage": 0
    },
    "meanNumberOfRequestsPerSecond": {
        "total": 0.007692307692307693,
        "ok": 0.007692307692307693,
        "ko": 0
    }
}
    },"req_purchase-a-trip-d01d7": {
        "type": "REQUEST",
        "name": "PURCHASE A TRIP FOR QUOTED PRICE.",
"path": "PURCHASE A TRIP FOR QUOTED PRICE.",
"pathFormatted": "req_purchase-a-trip-d01d7",
"stats": {
    "name": "PURCHASE A TRIP FOR QUOTED PRICE.",
    "numberOfRequests": {
        "total": 1,
        "ok": 1,
        "ko": 0
    },
    "minResponseTime": {
        "total": 753,
        "ok": 753,
        "ko": 0
    },
    "maxResponseTime": {
        "total": 753,
        "ok": 753,
        "ko": 0
    },
    "meanResponseTime": {
        "total": 753,
        "ok": 753,
        "ko": 0
    },
    "standardDeviation": {
        "total": 0,
        "ok": 0,
        "ko": 0
    },
    "percentiles1": {
        "total": 753,
        "ok": 753,
        "ko": 0
    },
    "percentiles2": {
        "total": 753,
        "ok": 753,
        "ko": 0
    },
    "percentiles3": {
        "total": 753,
        "ok": 753,
        "ko": 0
    },
    "percentiles4": {
        "total": 753,
        "ok": 753,
        "ko": 0
    },
    "group1": {
        "name": "t < 800 ms",
        "count": 1,
        "percentage": 100
    },
    "group2": {
        "name": "800 ms < t < 1200 ms",
        "count": 0,
        "percentage": 0
    },
    "group3": {
        "name": "t > 1200 ms",
        "count": 0,
        "percentage": 0
    },
    "group4": {
        "name": "failed",
        "count": 0,
        "percentage": 0
    },
    "meanNumberOfRequestsPerSecond": {
        "total": 0.007692307692307693,
        "ok": 0.007692307692307693,
        "ko": 0
    }
}
    },"req_fetch-trip-info-c4431": {
        "type": "REQUEST",
        "name": "FETCH TRIP INFO OF MY PURCHASED TRIP.",
"path": "FETCH TRIP INFO OF MY PURCHASED TRIP.",
"pathFormatted": "req_fetch-trip-info-c4431",
"stats": {
    "name": "FETCH TRIP INFO OF MY PURCHASED TRIP.",
    "numberOfRequests": {
        "total": 1,
        "ok": 1,
        "ko": 0
    },
    "minResponseTime": {
        "total": 730,
        "ok": 730,
        "ko": 0
    },
    "maxResponseTime": {
        "total": 730,
        "ok": 730,
        "ko": 0
    },
    "meanResponseTime": {
        "total": 730,
        "ok": 730,
        "ko": 0
    },
    "standardDeviation": {
        "total": 0,
        "ok": 0,
        "ko": 0
    },
    "percentiles1": {
        "total": 730,
        "ok": 730,
        "ko": 0
    },
    "percentiles2": {
        "total": 730,
        "ok": 730,
        "ko": 0
    },
    "percentiles3": {
        "total": 730,
        "ok": 730,
        "ko": 0
    },
    "percentiles4": {
        "total": 730,
        "ok": 730,
        "ko": 0
    },
    "group1": {
        "name": "t < 800 ms",
        "count": 1,
        "percentage": 100
    },
    "group2": {
        "name": "800 ms < t < 1200 ms",
        "count": 0,
        "percentage": 0
    },
    "group3": {
        "name": "t > 1200 ms",
        "count": 0,
        "percentage": 0
    },
    "group4": {
        "name": "failed",
        "count": 0,
        "percentage": 0
    },
    "meanNumberOfRequestsPerSecond": {
        "total": 0.007692307692307693,
        "ok": 0.007692307692307693,
        "ko": 0
    }
}
    },"req_disrupt-purchas-8153e": {
        "type": "REQUEST",
        "name": "DISRUPT PURCHASED TRIP.",
"path": "DISRUPT PURCHASED TRIP.",
"pathFormatted": "req_disrupt-purchas-8153e",
"stats": {
    "name": "DISRUPT PURCHASED TRIP.",
    "numberOfRequests": {
        "total": 1,
        "ok": 1,
        "ko": 0
    },
    "minResponseTime": {
        "total": 396,
        "ok": 396,
        "ko": 0
    },
    "maxResponseTime": {
        "total": 396,
        "ok": 396,
        "ko": 0
    },
    "meanResponseTime": {
        "total": 396,
        "ok": 396,
        "ko": 0
    },
    "standardDeviation": {
        "total": 0,
        "ok": 0,
        "ko": 0
    },
    "percentiles1": {
        "total": 396,
        "ok": 396,
        "ko": 0
    },
    "percentiles2": {
        "total": 396,
        "ok": 396,
        "ko": 0
    },
    "percentiles3": {
        "total": 396,
        "ok": 396,
        "ko": 0
    },
    "percentiles4": {
        "total": 396,
        "ok": 396,
        "ko": 0
    },
    "group1": {
        "name": "t < 800 ms",
        "count": 1,
        "percentage": 100
    },
    "group2": {
        "name": "800 ms < t < 1200 ms",
        "count": 0,
        "percentage": 0
    },
    "group3": {
        "name": "t > 1200 ms",
        "count": 0,
        "percentage": 0
    },
    "group4": {
        "name": "failed",
        "count": 0,
        "percentage": 0
    },
    "meanNumberOfRequestsPerSecond": {
        "total": 0.007692307692307693,
        "ok": 0.007692307692307693,
        "ko": 0
    }
}
    },"req_fetch-rebooking-bd812": {
        "type": "REQUEST",
        "name": "FETCH REBOOKING OPPORTUNITY FROM FREEBIRD.",
"path": "FETCH REBOOKING OPPORTUNITY FROM FREEBIRD.",
"pathFormatted": "req_fetch-rebooking-bd812",
"stats": {
    "name": "FETCH REBOOKING OPPORTUNITY FROM FREEBIRD.",
    "numberOfRequests": {
        "total": 2,
        "ok": 1,
        "ko": 1
    },
    "minResponseTime": {
        "total": 751,
        "ok": 751,
        "ko": 823
    },
    "maxResponseTime": {
        "total": 823,
        "ok": 751,
        "ko": 823
    },
    "meanResponseTime": {
        "total": 787,
        "ok": 751,
        "ko": 823
    },
    "standardDeviation": {
        "total": 36,
        "ok": 0,
        "ko": 0
    },
    "percentiles1": {
        "total": 787,
        "ok": 751,
        "ko": 823
    },
    "percentiles2": {
        "total": 805,
        "ok": 751,
        "ko": 823
    },
    "percentiles3": {
        "total": 819,
        "ok": 751,
        "ko": 823
    },
    "percentiles4": {
        "total": 822,
        "ok": 751,
        "ko": 823
    },
    "group1": {
        "name": "t < 800 ms",
        "count": 1,
        "percentage": 50
    },
    "group2": {
        "name": "800 ms < t < 1200 ms",
        "count": 0,
        "percentage": 0
    },
    "group3": {
        "name": "t > 1200 ms",
        "count": 0,
        "percentage": 0
    },
    "group4": {
        "name": "failed",
        "count": 1,
        "percentage": 50
    },
    "meanNumberOfRequestsPerSecond": {
        "total": 0.015384615384615385,
        "ok": 0.007692307692307693,
        "ko": 0.007692307692307693
    }
}
    },"req_fetch-the-avail-685c4": {
        "type": "REQUEST",
        "name": "FETCH THE AVAILABLE REBOOKING OPTIONS FOR MY TRIP.",
"path": "FETCH THE AVAILABLE REBOOKING OPTIONS FOR MY TRIP.",
"pathFormatted": "req_fetch-the-avail-685c4",
"stats": {
    "name": "FETCH THE AVAILABLE REBOOKING OPTIONS FOR MY TRIP.",
    "numberOfRequests": {
        "total": 1,
        "ok": 1,
        "ko": 0
    },
    "minResponseTime": {
        "total": 7301,
        "ok": 7301,
        "ko": 0
    },
    "maxResponseTime": {
        "total": 7301,
        "ok": 7301,
        "ko": 0
    },
    "meanResponseTime": {
        "total": 7301,
        "ok": 7301,
        "ko": 0
    },
    "standardDeviation": {
        "total": 0,
        "ok": 0,
        "ko": 0
    },
    "percentiles1": {
        "total": 7301,
        "ok": 7301,
        "ko": 0
    },
    "percentiles2": {
        "total": 7301,
        "ok": 7301,
        "ko": 0
    },
    "percentiles3": {
        "total": 7301,
        "ok": 7301,
        "ko": 0
    },
    "percentiles4": {
        "total": 7301,
        "ok": 7301,
        "ko": 0
    },
    "group1": {
        "name": "t < 800 ms",
        "count": 0,
        "percentage": 0
    },
    "group2": {
        "name": "800 ms < t < 1200 ms",
        "count": 0,
        "percentage": 0
    },
    "group3": {
        "name": "t > 1200 ms",
        "count": 1,
        "percentage": 100
    },
    "group4": {
        "name": "failed",
        "count": 0,
        "percentage": 0
    },
    "meanNumberOfRequestsPerSecond": {
        "total": 0.007692307692307693,
        "ok": 0.007692307692307693,
        "ko": 0
    }
}
    },"req_select-a-option-4fdfb": {
        "type": "REQUEST",
        "name": "SELECT A OPTION FROM AVAILABLE OPTIONS.",
"path": "SELECT A OPTION FROM AVAILABLE OPTIONS.",
"pathFormatted": "req_select-a-option-4fdfb",
"stats": {
    "name": "SELECT A OPTION FROM AVAILABLE OPTIONS.",
    "numberOfRequests": {
        "total": 1,
        "ok": 1,
        "ko": 0
    },
    "minResponseTime": {
        "total": 479,
        "ok": 479,
        "ko": 0
    },
    "maxResponseTime": {
        "total": 479,
        "ok": 479,
        "ko": 0
    },
    "meanResponseTime": {
        "total": 479,
        "ok": 479,
        "ko": 0
    },
    "standardDeviation": {
        "total": 0,
        "ok": 0,
        "ko": 0
    },
    "percentiles1": {
        "total": 479,
        "ok": 479,
        "ko": 0
    },
    "percentiles2": {
        "total": 479,
        "ok": 479,
        "ko": 0
    },
    "percentiles3": {
        "total": 479,
        "ok": 479,
        "ko": 0
    },
    "percentiles4": {
        "total": 479,
        "ok": 479,
        "ko": 0
    },
    "group1": {
        "name": "t < 800 ms",
        "count": 1,
        "percentage": 100
    },
    "group2": {
        "name": "800 ms < t < 1200 ms",
        "count": 0,
        "percentage": 0
    },
    "group3": {
        "name": "t > 1200 ms",
        "count": 0,
        "percentage": 0
    },
    "group4": {
        "name": "failed",
        "count": 0,
        "percentage": 0
    },
    "meanNumberOfRequestsPerSecond": {
        "total": 0.007692307692307693,
        "ok": 0.007692307692307693,
        "ko": 0
    }
}
    }
}

}